<?xml version="1.0" encoding="utf-8"?>
<ldml xmlns:sil="urn://www.sil.org/ldml/0.1">
	<identity>
		<version number="0.0.1"/>
		<generation date="2018-11-20 21:02:41"/>
		<language type="ikw"/>
		<special>
			<sil:identity defaultRegion="NG" script="Latn" draft="generated"/>
		</special>
	</identity>
	<localeDisplayNames>
		<languages>
			<language type="ikw">Ikwerre</language>
		</languages>
		<special>
			<sil:names>
				<sil:name xml:lang="en">Ikwere</sil:name>
			</sil:names>
		</special>
	</localeDisplayNames>
	<layout>
		<orientation>
			<characterOrder>left-to-right</characterOrder>
		</orientation>
	</layout>
	<characters>
		<exemplarCharacters draft="unconfirmed">[a á b c d e é ẹ {ẹ́} f g h i í ị {ị́} j k l m n o ó ọ {ọ́} p r s t u ú ụ {ụ́} v w y z]</exemplarCharacters>
		<exemplarCharacters type="auxiliary" draft="unconfirmed">[q x]</exemplarCharacters>
		<exemplarCharacters type="index">[A Á B C D E É Ẹ {Ẹ́} F G H I Í Ị {Ị́} J K L M N O Ó Ọ {Ọ́} P R S T U Ú Ụ {Ụ́} V W Y Z]</exemplarCharacters>
		<exemplarCharacters type="punctuation">[! ' ( ) , \- . \: ; ? \[ \] — ‘ ’ “ ”]</exemplarCharacters>
		<special>
			<sil:exemplarCharacters type="footnotes">[a b c d e f g h i j k l m n o p r s t u v w y z]</sil:exemplarCharacters>
		</special>
	</characters>
	<delimiters>
		<quotationStart>“</quotationStart>
		<quotationEnd>”</quotationEnd>
		<alternateQuotationStart>‘</alternateQuotationStart>
		<alternateQuotationEnd>’</alternateQuotationEnd>
		<special>
			<sil:matched-pairs>
				<sil:matched-pair open="(" close=")" paraClose="false"/>
				<sil:matched-pair open="[" close="]" paraClose="false"/>
				<sil:matched-pair open="{" close="}" paraClose="false"/>
			</sil:matched-pairs>
			<sil:punctuation-patterns>
				<sil:punctuation-pattern pattern="!_" context="final"/>
				<sil:punctuation-pattern pattern="!”_" context="final"/>
				<sil:punctuation-pattern pattern="!”_(" context="medial"/>
				<sil:punctuation-pattern pattern="&apos;" context="medial"/>
				<sil:punctuation-pattern pattern="),_" context="final"/>
				<sil:punctuation-pattern pattern="),_“" context="medial"/>
				<sil:punctuation-pattern pattern=")._" context="final"/>
				<sil:punctuation-pattern pattern=").”_" context="final"/>
				<sil:punctuation-pattern pattern=")_" context="final"/>
				<sil:punctuation-pattern pattern=",_" context="final"/>
				<sil:punctuation-pattern pattern=",_(" context="medial"/>
				<sil:punctuation-pattern pattern=",_//_" context="final"/>
				<sil:punctuation-pattern pattern=",_‘" context="medial"/>
				<sil:punctuation-pattern pattern=",_“" context="medial"/>
				<sil:punctuation-pattern pattern=",_“‘" context="medial"/>
				<sil:punctuation-pattern pattern=",’_" context="final"/>
				<sil:punctuation-pattern pattern=",”_" context="final"/>
				<sil:punctuation-pattern pattern="-" context="medial"/>
				<sil:punctuation-pattern pattern=".)_" context="final"/>
				<sil:punctuation-pattern pattern="..._" context="final"/>
				<sil:punctuation-pattern pattern="...’”_(" context="medial"/>
				<sil:punctuation-pattern pattern=".]_" context="final"/>
				<sil:punctuation-pattern pattern="._" context="final"/>
				<sil:punctuation-pattern pattern="._(" context="medial"/>
				<sil:punctuation-pattern pattern="._[" context="medial"/>
				<sil:punctuation-pattern pattern="._“" context="medial"/>
				<sil:punctuation-pattern pattern=".’_" context="final"/>
				<sil:punctuation-pattern pattern=".’”_" context="final"/>
				<sil:punctuation-pattern pattern=".”]_" context="final"/>
				<sil:punctuation-pattern pattern=".”_" context="final"/>
				<sil:punctuation-pattern pattern=".”_(" context="medial"/>
				<sil:punctuation-pattern pattern=".”_[" context="medial"/>
				<sil:punctuation-pattern pattern=".”_“" context="medial"/>
				<sil:punctuation-pattern pattern="/" context="medial"/>
				<sil:punctuation-pattern pattern=":_" context="final"/>
				<sil:punctuation-pattern pattern=";_" context="final"/>
				<sil:punctuation-pattern pattern="?)_" context="final"/>
				<sil:punctuation-pattern pattern="?_" context="final"/>
				<sil:punctuation-pattern pattern="?_(" context="medial"/>
				<sil:punctuation-pattern pattern="?_“" context="medial"/>
				<sil:punctuation-pattern pattern="?’_" context="final"/>
				<sil:punctuation-pattern pattern="?’_(" context="medial"/>
				<sil:punctuation-pattern pattern="?’”_" context="final"/>
				<sil:punctuation-pattern pattern="?’”_“" context="medial"/>
				<sil:punctuation-pattern pattern="?”_" context="final"/>
				<sil:punctuation-pattern pattern="?”_(" context="medial"/>
				<sil:punctuation-pattern pattern="]._" context="final"/>
				<sil:punctuation-pattern pattern="]_" context="final"/>
				<sil:punctuation-pattern pattern="_(" context="init"/>
				<sil:punctuation-pattern pattern="_..._" context="isolate"/>
				<sil:punctuation-pattern pattern="_//_" context="isolate"/>
				<sil:punctuation-pattern pattern="_/_" context="isolate"/>
				<sil:punctuation-pattern pattern="_[" context="init"/>
				<sil:punctuation-pattern pattern="_[_" context="isolate"/>
				<sil:punctuation-pattern pattern="_]_" context="isolate"/>
				<sil:punctuation-pattern pattern="_‘" context="init"/>
				<sil:punctuation-pattern pattern="_“" context="init"/>
				<sil:punctuation-pattern pattern="_“‘" context="init"/>
				<sil:punctuation-pattern pattern="‌" context="medial"/>
				<sil:punctuation-pattern pattern="‍" context="medial"/>
				<sil:punctuation-pattern pattern="’?_" context="final"/>
				<sil:punctuation-pattern pattern="’?”_" context="final"/>
				<sil:punctuation-pattern pattern="’_" context="final"/>
				<sil:punctuation-pattern pattern="’_(" context="medial"/>
				<sil:punctuation-pattern pattern="”?_" context="final"/>
				<sil:punctuation-pattern pattern="”_" context="final"/>
				<sil:punctuation-pattern pattern="”_(" context="medial"/>
			</sil:punctuation-patterns>
			<sil:quotation-marks paraContinueType="all">
				<sil:quotationContinue>“</sil:quotationContinue>
				<sil:alternateQuotationContinue>‘</sil:alternateQuotationContinue>
				<sil:quotation open="“" close="”" continue="“" level="3"/>
			</sil:quotation-marks>
		</special>
	</delimiters>
	<collations>
		<collation type="standard">
			<cr><![CDATA[
				&C < ch <<< Ch <<< CH
				&É < ẹ <<< Ẹ << ẹ́ <<< Ẹ́
				&G < gb <<< Gb <<< GB < gh <<< Gh <<< GH
				&Í < ị <<< Ị << ị́ <<< Ị́
				&K < kp <<< Kp <<< KP < kw <<< Kw <<< KW
				&M < mm <<< Mm <<< MM
				&N << n̄ <<< N̄ < nn <<< Nn <<< NN < nw <<< Nw <<< NW
				&Ó < ọ <<< Ọ << ọ́ <<< Ọ́
				&Ú < ụ <<< Ụ << ụ́ <<< Ụ́
			]]></cr>
			<special>
				<sil:simple>a/A á/Á
				b/B
				c/C
				ch
				d/D
				e/E é/É
				ẹ/Ẹ ẹ́
				f/F
				g/G
				gb
				gh
				h/H
				i/I í
				ị/Ị ị́
				j/J
				k/K
				kp
				kw
				l/L
				m/M
				mm
				n/N n̄
				nn
				nw
				o/O ó/Ó
				ọ/Ọ ọ́
				p/P
				r/R
				s/S
				t/T
				u/U ú/Ú
				ụ/Ụ ụ́
				v/V
				w/W
				y/Y
				z/Z</sil:simple>
			</special>
		</collation>
	</collations>
	<special>
		<sil:external-resources>
			<sil:font name="Charis SIL" types="default">
				<sil:url>https://lff.api.languagetechnology.org/family/charissil</sil:url>
			</sil:font>
			<sil:font name="Noto Sans">
				<!--types="ui"-->
				<sil:url>https://github.com/googlefonts/noto-fonts/raw/main/hinted/ttf/NotoSans/NotoSans-Regular.ttf</sil:url>
			</sil:font>
			<sil:font name="Noto Serif">
				<sil:url>https://github.com/googlefonts/noto-fonts/raw/main/hinted/ttf/NotoSerif/NotoSerif-Regular.ttf</sil:url>
			</sil:font>
			<sil:kbd id="sil_nigeria_dot" type="kmp">
				<sil:url>https://keyman.com/go/keyboard/sil_nigeria_dot/download/kmp</sil:url>
			</sil:kbd>
		</sil:external-resources>
	</special>
</ldml>
