<?xml version="1.0" encoding="utf-8"?>
<ldml xmlns:sil="urn://www.sil.org/ldml/0.1">
	<identity>
		<special>
			<sil:identity uid="unilex"/>
		</special>
		<generation date="2018-11-21 00:22:38"/>
		<language type="ht"/>
		<script>Latn</script>
	</identity>
	<characters>
		<exemplarCharacters draft="generated">[a à b c d e è f g h i j k l m n o ò p r s t u v w y z]</exemplarCharacters>
		<exemplarCharacters type="index" draft="generated">[A À B C D E È F G H I J K L M N O Ò P R S T U V W Y Z]</exemplarCharacters>
		<exemplarCharacters type="punctuation" draft="generated">[']</exemplarCharacters>
	</characters>
</ldml>
