<?xml version="1.0" encoding="utf-8"?>
<ldml xmlns:sil="urn://www.sil.org/ldml/0.1">
	<identity>
		<version number="20210903.0403" draft="unconfirmed"/>
		<language type="hus" draft="unconfirmed"/>
		<variant type="x-potosino" draft="unconfirmed"/>
		<special>
			<sil:identity draft="generated"/>
		</special>
	</identity>
	<layout>
		<orientation>
			<characterOrder>left-to-right</characterOrder>
		</orientation>
	</layout>
	<characters>
		<exemplarCharacters>[a á b c d e é f g h i í j k l m n ñ o ó p q r s t u ú v x y z]</exemplarCharacters>
		<exemplarCharacters type="punctuation">[― , \: ? ¿ . ’]</exemplarCharacters>
		<exemplarCharacters type="index">[A Á B C D E É F G H I Í J K L M N Ñ O Ó P Q R S T U Ú V X Y Z]</exemplarCharacters>
	</characters>
	<delimiters>
		<quotationStart>“</quotationStart>
		<quotationEnd>”</quotationEnd>
		<alternateQuotationStart>‘</alternateQuotationStart>
		<alternateQuotationEnd>’</alternateQuotationEnd>
		<special>
			<sil:matched-pairs>
				<sil:matched-pair open="(" close=")" paraClose="false"/>
				<sil:matched-pair open="[" close="]" paraClose="false"/>
				<sil:matched-pair open="{" close="}" paraClose="false"/>
			</sil:matched-pairs>
			<sil:punctuation-patterns>
				<sil:punctuation-pattern pattern=")_" context="final"/>
				<sil:punctuation-pattern pattern=",_" context="final"/>
				<sil:punctuation-pattern pattern=",_¿" context="medial"/>
				<sil:punctuation-pattern pattern="._" context="final"/>
				<sil:punctuation-pattern pattern="._¿" context="medial"/>
				<sil:punctuation-pattern pattern=":_" context="final"/>
				<sil:punctuation-pattern pattern=":_¿" context="medial"/>
				<sil:punctuation-pattern pattern=":_―" context="medial"/>
				<sil:punctuation-pattern pattern=";_" context="final"/>
				<sil:punctuation-pattern pattern="?_" context="final"/>
				<sil:punctuation-pattern pattern="?_¿" context="medial"/>
				<sil:punctuation-pattern pattern="_(" context="init"/>
				<sil:punctuation-pattern pattern="_¿" context="init"/>
				<sil:punctuation-pattern pattern="_―" context="init"/>
				<sil:punctuation-pattern pattern="_―¿" context="init"/>
				<sil:punctuation-pattern pattern="‌" context="medial"/>
				<sil:punctuation-pattern pattern="‍" context="medial"/>
				<sil:punctuation-pattern pattern="’" context="medial"/>
				<sil:punctuation-pattern pattern="’,_" context="final"/>
				<sil:punctuation-pattern pattern="’._" context="final"/>
				<sil:punctuation-pattern pattern="’._¿" context="medial"/>
				<sil:punctuation-pattern pattern="’:_" context="final"/>
				<sil:punctuation-pattern pattern="’:_¿" context="medial"/>
				<sil:punctuation-pattern pattern="’?_" context="final"/>
				<sil:punctuation-pattern pattern="’?_¿" context="medial"/>
				<sil:punctuation-pattern pattern="’_" context="final"/>
			</sil:punctuation-patterns>
			<sil:quotation-marks paraContinueType="all">
				<sil:quotationContinue>“</sil:quotationContinue>
				<sil:alternateQuotationContinue>‘</sil:alternateQuotationContinue>
				<sil:quotation open="“" close="”" continue="“" level="3"/>
			</sil:quotation-marks>
		</special>
	</delimiters>
	<collations>
		<defaultCollation>standard</defaultCollation>
	</collations>
	<special>
		<sil:external-resources>
			<sil:font name="Charis SIL AmArea"/>
			<sil:font name="Charis SIL AmArea" types="default" size="0.85"/>
		</sil:external-resources>
	</special>
</ldml>
