<?xml version="1.0" encoding="utf-8"?>
<ldml xmlns:sil="urn://www.sil.org/ldml/0.1">
	<identity>
		<special>
			<sil:identity uid="unilex"/>
		</special>
		<generation date="2018-11-21 00:23:17"/>
		<language type="ker"/>
		<script>Latn</script>
	</identity>
	<characters>
		<exemplarCharacters draft="generated">[a á ã b c d e é ẽ f g h i ĩ j k l m n o ó õ p r s t u ú v w y z ŋ ɓ ɗ ə {ə̃}]</exemplarCharacters>
		<exemplarCharacters type="index" draft="generated">[A Á Ã B C D E É Ẽ F G H I Ĩ J K L M N O Ó Õ P R S T U Ú V W Y Z Ŋ Ɓ Ɗ Ə {Ə̃}]</exemplarCharacters>
		<exemplarCharacters type="punctuation" draft="generated">[']</exemplarCharacters>
	</characters>
</ldml>
