<?xml version="1.0" encoding="utf-8"?>
<!-- Please enter language data in the fields below.  All data should be entered in English -->
<ldml>
	<identity>
		<version number="0.0.1"/>
		<!-- name.en(emk)="Eastern Maninkakan" -->
		<language type="emk"/>
		<special xmlns:sil="urn://www.sil.org/ldml/0.1">
			<sil:identity defaultRegion="GW" script="Latn"/>
		</special>
	</identity>
	<characters>
		<exemplarCharacters>[a b c d e ɛ f g {gb} h i j k l m n ɲ o ɔ p r s t u w y]</exemplarCharacters>
		<exemplarCharacters type="auxiliary">[q v x z]</exemplarCharacters>
	</characters>
</ldml>
