<?xml version="1.0" encoding="utf-8"?>
<!-- Please enter language data in the fields below.  All data should be entered in English -->
<ldml xmlns:sil="urn://www.sil.org/ldml/0.1">
	<identity>
		<language type="lns"/>
		<special>
			<sil:identity defaultRegion="CM"/>
		</special>
	</identity>
	<characters>
		<exemplarCharacters type="auxiliary" draft="unconfirmed">[q x z]</exemplarCharacters>
		<exemplarCharacters draft="unconfirmed">[a b {bv} c d {dz} e ə f g {gb} {gh} {ghv} {gv} h i j k {kf} {kp} l m {mv} n {ny} ŋ o p r s {sh} t {ts} u v w y ʼ]</exemplarCharacters>
	</characters>
</ldml>
