<?xml version="1.0" encoding="utf-8"?>
<!-- Please enter language data in the fields below.  All data should be entered in English -->
<ldml xmlns:sil="urn://www.sil.org/ldml/0.1">
	<identity>
		<version number="0.0.1"/>
		<!-- name.en(jra)="Jarai" -->
		<language type="jra"/>
		<special>
			<sil:identity defaultRegion="VN" script="Latn"/>
		</special>
	</identity>
	<localeDisplayNames>
		<languages>
			<language type="jra">Jơrai</language>
		</languages>
		<special>
			<sil:names>
				<sil:name xml:lang="en">Jarai</sil:name>
			</sil:names>
		</special>
	</localeDisplayNames>
	<characters>
		<exemplarCharacters>[a {ă} {â} b ƀ č d đ e {ĕ} {ê} {ê̆} g h i {ĭ} j {dj} k l m n {ñ} {ng} o {ŏ} {ô} {ô̆} {ơ} {ơ̆} p r s t u {ŭ} {ư} {ư̆} w y]</exemplarCharacters>
		<exemplarCharacters type="auxiliary">[c {c̆} f q v x z]</exemplarCharacters>
		<exemplarCharacters type="punctuation">[\- – , ; \: ! ? . … ' ‘ ’ “ ” ( ) \[ \]]</exemplarCharacters>
		<exemplarCharacters type="index">[A Â B Ƀ C Č D Đ E Ê F G H I J K L M N Ñ O Ô Ơ P R S T U Ư W Y Z]</exemplarCharacters>
	</characters>
	<delimiters>
		<quotationStart>“</quotationStart>
		<quotationEnd>”</quotationEnd>
		<alternateQuotationStart>‘</alternateQuotationStart>
		<alternateQuotationEnd>’</alternateQuotationEnd>
	</delimiters>
	<special>
		<sil:external-resources>
			<sil:font name="Charis SIL" types="default" features="cv82=0 ss04=0">
				<sil:url>https://wirl.api.sil.org/CharisSILReg&amp;type=ttf</sil:url>
			</sil:font>
			<sil:font name="Noto Sans">
				<!--types="ui"-->
				<sil:url>https://github.com/googlefonts/noto-fonts/raw/main/hinted/ttf/NotoSans/NotoSans-Regular.ttf</sil:url>
			</sil:font>
			<sil:font name="Noto Serif">
				<sil:url>https://github.com/googlefonts/noto-fonts/raw/main/hinted/ttf/NotoSerif/NotoSerif-Regular.ttf</sil:url>
			</sil:font>
			<sil:kbd id="jorai" type="kmp">
				<sil:url draft="generated">https://keyman.com/go/keyboard/jorai/download/kmp</sil:url>
			</sil:kbd>
		</sil:external-resources>
	</special>
</ldml>
