<?xml version="1.0" encoding="utf-8"?>
<!-- Please enter language data in the fields below.  All data should be entered in English -->
<ldml xmlns:sil="urn://www.sil.org/ldml/0.1">
	<identity>
		<version number="0.0.1"/>
		<!-- name.en(sav)="Saafi-Saafi" -->
		<language type="sav"/>
	</identity>
	<layout>
		<!--  Enter the orientation attributes  -->
		<orientation>
			<characterOrder>right-to-left</characterOrder>
		</orientation>
	</layout>
	<characters>
		<exemplarCharacters>[\u064E \u08F5 \u064F \u0650 \u08F6 \u08F7 \u08F9 ا ب ࢠ ت ݖ ج ڃ د ر س ط ݝ ف ک گ ل م ن ݧ ہ ي {مب} {ند} {ݧج} {ݝگ}]</exemplarCharacters>
		<exemplarCharacters type="auxiliary">[\u200C\u200D\u200E\u200F]</exemplarCharacters>
	</characters>
</ldml>
