<?xml version="1.0" encoding="UTF-8"?>
<!DOCTYPE ldml SYSTEM "../../common/dtd/ldml.dtd">
<ldml>
  <identity>
    <language name="Bozo, Tiéyaxo" code="boz" />
    <script name="Latin" code="Latn" />
  </identity>
  <contacts>
    <contact name="Anne-Marie" email="anne-marie_klade@sil.org" />
  </contacts>
  <comments>
    <entry date="2017-02-08" name="ScriptSource moderator" comment="Auto-generated from ScriptSource character-list entry (UID lflg5qxx6y) submitted by anne-marie_klade" />
  </comments>
  <status value="Draft"/>
  <characters>
    <exemplarCharacters>a b d e ɛ f g h i j k l m n ɲ ŋ o ɔ p r s t u w x y</exemplarCharacters>
    <exemplarCharacters type="auxiliary">c v z</exemplarCharacters>
    <exemplarCharacters type="index">A B D E Ɛ F G H I J K L M N Ɲ Ŋ O Ɔ P R S T U W X Y</exemplarCharacters>
    <exemplarCharacters type="punctuation">. , ; : ? ! " " ' ' «» - ( )</exemplarCharacters>
  </characters>
</ldml>
