<?xml version="1.0" encoding="utf-8"?>
<!-- Please enter language data in the fields below.  All data should be entered in English -->
<ldml>
	<identity>
		<version number="0.0.1"/>
		<!-- name.en(mhi)="Ma'di" -->
		<language type="mhi"/>
		<special xmlns:sil="urn://www.sil.org/ldml/0.1">
			<sil:identity defaultRegion="UG"/>
		</special>
	</identity>
	<characters>
		<exemplarCharacters>[a {ä} b d {ʤ} e ɛ f g i ɩ k {kp} l m n {ny} ŋ o ɔ p r s t {tʃ} u ʋ v w y z ʼ]</exemplarCharacters>
		<exemplarCharacters type="auxiliary">[c j q x]</exemplarCharacters>
	</characters>
</ldml>
