<?xml version="1.0" encoding="utf-8"?>
<ldml xmlns:sil="urn://www.sil.org/ldml/0.1">
	<identity>
		<version number="0.0.1"/>
		<generation date="2018-11-20 21:55:26"/>
		<language type="mkn"/>
		<special>
			<sil:identity defaultRegion="ID" script="Latn" draft="generated"/>
		</special>
	</identity>
	<localeDisplayNames>
		<languages>
			<language type="mkn">Kupang</language>
		</languages>
		<special>
			<sil:names>
				<sil:name xml:lang="en">Kupang Malay</sil:name>
			</sil:names>
		</special>
	</localeDisplayNames>
	<layout>
		<orientation>
			<characterOrder>left-to-right</characterOrder>
		</orientation>
	</layout>
	<characters>
		<exemplarCharacters>[a á b c d e é f g h i í j k l m n o ó p r s t u ú w y z ꞌ]</exemplarCharacters>
		<exemplarCharacters type="punctuation">[! ( ) , \- . \: ; ? \[ \] — ‘ ’ “ ”]</exemplarCharacters>
		<exemplarCharacters type="index">[A Á B C D E É F G H I Í J K L M N O Ó P R S T U Ú W Y Z Ꞌ]</exemplarCharacters>
	</characters>
	<special>
		<sil:external-resources>
			<sil:font name="Charis SIL" types="default" size="0.7">
				<sil:url>https://wirl.api.sil.org/CharisSILReg&amp;type=ttf</sil:url>
			</sil:font>
			<sil:font name="Noto Sans" types="ui">
				<sil:url>https://github.com/googlefonts/noto-fonts/raw/main/hinted/ttf/NotoSans/NotoSans-Regular.ttf</sil:url>
			</sil:font>
			<sil:font name="Noto Serif">
				<sil:url>https://github.com/googlefonts/noto-fonts/raw/main/hinted/ttf/NotoSerif/NotoSerif-Regular.ttf</sil:url>
			</sil:font>
		</sil:external-resources>
	</special>
</ldml>
