<?xml version="1.0" encoding="utf-8"?>
<!-- Please enter language data in the fields below.  All data should be entered in English -->
<ldml xmlns:sil="urn://www.sil.org/ldml/0.1">
	<identity>
		<version number="0.0.1"/>
		<!-- name.en(cr)="Cree" -->
		<language type="cr"/>
		<script type="Cans"/>
		<special>
			<sil:identity defaultRegion="CA"/>
		</special>
	</identity>
	<special>
		<sil:external-resources>
			<sil:font name="Aboriginal Sans">
				<sil:url>https://wirl.api.sil.org/AboriginalSans</sil:url>
			</sil:font>
		</sil:external-resources>
	</special>
</ldml>
